kaze/__init__.py
kaze/curl_utils.py
kaze/file_utils.py
kaze/kaze_cli.py
kaze/utils.py
kaze_specs/__init__.py
kaze_specs/test_kaze.py
kaze-0.0.14.dist-info/LICENSE
kaze-0.0.14.dist-info/METADATA
kaze-0.0.14.dist-info/WHEEL
kaze-0.0.14.dist-info/entry_points.txt
kaze-0.0.14.dist-info/top_level.txt
kaze-0.0.14.dist-info/RECORD
