Metadata-Version: 2.1
Name: kaze
Version: 0.0.14
Summary: CLI for Managing The Data Dependency of Deep Learning Projects
Home-page: https://github.com/geyang/dew
Author: Ge Yang
Author-email: yangge1987@gmail.com
License: Copyright 2022 Ge Yang        
Keywords: datasets,data,data science
Platform: UNKNOWN
Classifier: Development Status :: 4 - Beta
Classifier: Intended Audience :: Science/Research
Classifier: Programming Language :: Python :: 3
License-File: LICENSE
Requires-Dist: click
Requires-Dist: pyyaml
Requires-Dist: termcolor
Requires-Dist: functional-notations
Requires-Dist: requests
Requires-Dist: params-proto
